aws_ec2_instance_reaper/__init__.py
aws_ec2_instance_reaper/__main__.py
aws_ec2_instance_reaper/aws.py
aws_ec2_instance_reaper/click_argument_types.py
aws_ec2_instance_reaper/logger.py
aws_ec2_instance_reaper/reaper.py
aws_ec2_instance_reaper/schema.py
aws_ec2_instance_reaper-0.1.4.dist-info/LICENSE
aws_ec2_instance_reaper-0.1.4.dist-info/METADATA
aws_ec2_instance_reaper-0.1.4.dist-info/WHEEL
aws_ec2_instance_reaper-0.1.4.dist-info/entry_points.txt
aws_ec2_instance_reaper-0.1.4.dist-info/top_level.txt
aws_ec2_instance_reaper-0.1.4.dist-info/RECORD
