Metadata-Version: 2.1
Name: aws-ec2-instance-reaper
Version: 0.1.4
Summary: reap dangling EC2 machines on AWS
Home-page: https://github.com/binxio/aws-ec2-instance-reaper
Author: Mark van Holsteijn
Author-email: mark@binx.io
License: BSD
Platform: any
Classifier: Development Status :: 4 - Beta
Classifier: Environment :: Console
Classifier: Intended Audience :: Developers
Classifier: License :: OSI Approved :: BSD License
Classifier: Operating System :: POSIX
Classifier: Operating System :: MacOS
Classifier: Operating System :: Unix
Classifier: Operating System :: Microsoft :: Windows
Classifier: Programming Language :: Python
Classifier: Programming Language :: Python :: 3
Classifier: Topic :: Software Development :: Libraries :: Python Modules
License-File: LICENSE
Requires-Dist: boto3
Requires-Dist: click
Requires-Dist: pytz
Requires-Dist: humanize
Requires-Dist: durations
Requires-Dist: jsonschema
